command_line.py
src/char_count_vp/__init__.py
src/char_count_vp/char_counter.py
char_counter_vp-0.0.5.dist-info/METADATA
char_counter_vp-0.0.5.dist-info/WHEEL
char_counter_vp-0.0.5.dist-info/licenses/LICENSE
char_counter_vp-0.0.5.dist-info/RECORD
